macimg/__init__.py
macimg/compositions.py
macimg/core.py
macimg/distortions.py
macimg/filters.py
macimg/generators.py
macimg/transforms.py
macimg-0.0.3.dist-info/LICENSE
macimg-0.0.3.dist-info/METADATA
macimg-0.0.3.dist-info/WHEEL
macimg-0.0.3.dist-info/top_level.txt
macimg-0.0.3.dist-info/RECORD
