Metadata-Version: 2.1
Name: macimg
Version: 0.0.3
Summary: A package for manipulating images using Objective-C frameworks
Home-page: https://github.com/SKaplanOfficial/macimg
Author: Stephen Kaplan
Author-email: stephen.kaplan@maine.edu
Project-URL: Bug Tracker, https://github.com/SKaplanOfficial/macimg/issues
Classifier: Programming Language :: Python :: 3
Classifier: License :: OSI Approved :: MIT License
Classifier: Operating System :: OS Independent
Requires-Python: >=3.10
License-File: LICENSE
